forecastga/__init__.py
forecastga/auto.py
forecastga/ensembles.py
forecastga/ga/__init__.py
forecastga/ga/account.py
forecastga/ga/auth/__init__.py
forecastga/ga/auth/credentials.py
forecastga/ga/auth/oauth.py
forecastga/ga/blueprint.py
forecastga/ga/columns.py
forecastga/ga/errors.py
forecastga/ga/query.py
forecastga/ga/realtime.yml
forecastga/ga/segments.py
forecastga/ga/utils/__init__.py
forecastga/ga/utils/date.py
forecastga/ga/utils/functional.py
forecastga/ga/utils/server.py
forecastga/ga/utils/string.py
forecastga/helpers/colab.py
forecastga/helpers/data.py
forecastga/helpers/ga_data.py
forecastga/helpers/holidays.py
forecastga/helpers/logging.py
forecastga/helpers/ssa.py
forecastga/models/__init__.py
forecastga/models/arima.py
forecastga/models/base.py
forecastga/models/gluonts.py
forecastga/models/hwaas.py
forecastga/models/hwams.py
forecastga/models/nbeats.py
forecastga/models/prophet.py
forecastga/models/prophet_boxcox.py
forecastga/models/pyaf.py
forecastga/models/sarima.py
forecastga/models/sarimax.py
forecastga/models/tats.py
forecastga/models/tbat.py
forecastga/models/tbatp1.py
forecastga/models/tbats1.py
forecastga/models/tbats2.py
forecastga/models/template.py
forecastga/stan/unix/prophet.stan
forecastga/stan/win/prophet.stan
forecastga-0.1.16.dist-info/LICENSE.md
forecastga-0.1.16.dist-info/WHEEL
forecastga-0.1.16.dist-info/METADATA
forecastga-0.1.16.dist-info/RECORD
