Metadata-Version: 2.1
Name: forecastga
Version: 0.1.16
Summary: A Python tool to forecast GA data using several popular timeseries models
Home-page: https://github.com/jroakes/ForecastGA
License: MIT
Keywords: google analytics,forecasting,python
Author: JR Oakes
Author-email: jroakes@gmail.com
Requires-Python: >=3.6.2,<4.0.0
Classifier: License :: OSI Approved :: MIT License
Classifier: Programming Language :: Python :: 3
Classifier: Programming Language :: Python :: 3.7
Classifier: Programming Language :: Python :: 3.8
Classifier: Programming Language :: Python :: 3.9
Requires-Dist: MarkupSafe (>=1.1.1,<2.0.0)
Requires-Dist: PyYAML (>=5.3.1,<6.0.0)
Requires-Dist: Werkzeug (>=1.0.1,<2.0.0)
Requires-Dist: addressable (>=1.4.2,<2.0.0)
Requires-Dist: colorama (>=0.4.4,<0.5.0)
Requires-Dist: fbprophet (>=0.7.1,<0.8.0)
Requires-Dist: gluonts (>=0.6.4,<0.7.0)
Requires-Dist: google-api-core (>=1.24.1,<2.0.0)
Requires-Dist: google-api-python-client (>=1.12.8,<2.0.0)
Requires-Dist: google-auth (>=1.24.0,<2.0.0)
Requires-Dist: google-auth-httplib2 (>=0.0.4,<0.0.5)
Requires-Dist: holidays (>=0.10.4,<0.11.0)
Requires-Dist: httplib2 (>=0.18.1,<0.19.0)
Requires-Dist: inspect-it (>=0.3.2,<0.4.0)
Requires-Dist: keyring (>=21.8.0,<22.0.0)
Requires-Dist: lightgbm (>=3.1.1,<4.0.0)
Requires-Dist: matplotlib (==3.2.2)
Requires-Dist: mxnet (>=1.7.0,<2.0.0)
Requires-Dist: nbeats-pytorch (>=1.3.1,<2.0.0)
Requires-Dist: numpy (==1.19.3)
Requires-Dist: oauth2client (>=4.1.3,<5.0.0)
Requires-Dist: pandas (==1.0.5)
Requires-Dist: pmdarima (>=1.8.0,<2.0.0)
Requires-Dist: prettytable (>=2.0.0,<3.0.0)
Requires-Dist: pylev (>=1.3.0,<2.0.0)
Requires-Dist: pystan (>=2.19.1,<3.0.0)
Requires-Dist: python-dateutil (>=2.8.1,<3.0.0)
Requires-Dist: requests (>=2.25.1,<3.0.0)
Requires-Dist: rsa (>=4.6,<5.0)
Requires-Dist: scikit-learn (>=0.24.0,<0.25.0)
Requires-Dist: scipy (==1.5.0)
Requires-Dist: seasonal (>=0.3.1,<0.4.0)
Requires-Dist: setuptools (>=51.1.1,<52.0.0)
Requires-Dist: snakify (>=1.1.1,<2.0.0)
Requires-Dist: statsmodels (>=0.12.1,<0.13.0)
Requires-Dist: tbats (>=1.1.0,<2.0.0)
Requires-Dist: torch (>=1.7.1,<2.0.0)
Requires-Dist: tqdm (>=4.55.1,<5.0.0)
Requires-Dist: tsfresh (>=0.17.0,<0.18.0)
Project-URL: Repository, https://github.com/jroakes/ForecastGA
